CHANGELOG.txt
LICENCE.txt
MANIFEST.in
README.txt
setup.py
ValidateConection/__init__.py
ValidateConection.egg-info/PKG-INFO
ValidateConection.egg-info/SOURCES.txt
ValidateConection.egg-info/dependency_links.txt
ValidateConection.egg-info/top_level.txt